{
    "parent": "minecraft:recipes/root",
    "criteria": {
        "has_blackstone_slab": {
            "conditions": {
                "items": [
                    {
                        "items": [
                            "minecraft:blackstone_slab"
                        ]
                    }
                ]
            },
            "trigger": "minecraft:inventory_changed"
        }
    },
    "requirements": [
        [
            "has_blackstone_slab"
        ]
    ],
    "rewards": {
        "recipes": [
            "half_to_full:normal/blackstone"
        ]
    }
}